ormir_pyvoxel-0.0.9.dist-info/licenses/LICENSE
voxel/__init__.py
voxel/config.py
voxel/device.py
voxel/med_volume.py
voxel/numpy_routines.py
voxel/orientation.py
voxel/io/__init__.py
voxel/io/dicom.py
voxel/io/format_io.py
voxel/io/http.py
voxel/io/nifti.py
voxel/utils/__init__.py
voxel/utils/collect_env.py
voxel/utils/env.py
voxel/utils/logger.py
voxel/utils/pixel_data.py
voxel/utils/realign.py
ormir_pyvoxel-0.0.9.dist-info/METADATA
ormir_pyvoxel-0.0.9.dist-info/WHEEL
ormir_pyvoxel-0.0.9.dist-info/top_level.txt
ormir_pyvoxel-0.0.9.dist-info/RECORD
