Metadata-Version: 2.4
Name: ormir-pyvoxel
Version: 0.0.9
Summary: I/O routines for medical imaging data
Home-page: https://github.com/ormir-mids/ormir-pyvoxel
Author: Arjun Desai, Francesco Santini, ORMIR Contributors
License: GNU
Project-URL: Documentation, https://pyvoxel.readthedocs.io/
Classifier: Programming Language :: Python :: 3
Classifier: License :: OSI Approved :: Apache Software License
Classifier: Operating System :: OS Independent
Requires-Python: >=3.6
License-File: LICENSE
Requires-Dist: dataclasses>=0.6
Requires-Dist: numpy
Requires-Dist: natsort
Requires-Dist: nibabel
Requires-Dist: packaging
Requires-Dist: pydicom>=2.2.0
Requires-Dist: PyYAML>=5.4.1
Requires-Dist: requests
Requires-Dist: tabulate
Requires-Dist: termcolor
Requires-Dist: tqdm>=4.42.0
Provides-Extra: dev
Requires-Dist: simpleitk; extra == "dev"
Requires-Dist: sigpy; extra == "dev"
Requires-Dist: h5py; extra == "dev"
Requires-Dist: coverage; extra == "dev"
Requires-Dist: flake8; extra == "dev"
Requires-Dist: flake8-bugbear; extra == "dev"
Requires-Dist: flake8-comprehensions; extra == "dev"
Requires-Dist: isort; extra == "dev"
Requires-Dist: black==22.8.0; extra == "dev"
Requires-Dist: click==8.0.2; extra == "dev"
Requires-Dist: pytest-cov>=2.10.1; extra == "dev"
Requires-Dist: pre-commit>=2.9.3; extra == "dev"
Requires-Dist: requests-mock; extra == "dev"
Requires-Dist: parameterized; extra == "dev"
Requires-Dist: twine; extra == "dev"
Provides-Extra: docs
Requires-Dist: mistune<2.0.0,>=0.8.1; extra == "docs"
Requires-Dist: sphinx; extra == "docs"
Requires-Dist: sphinxcontrib.bibtex; extra == "docs"
Requires-Dist: m2r2; extra == "docs"
Provides-Extra: optional
Requires-Dist: scipy; extra == "optional"
Dynamic: author
Dynamic: classifier
Dynamic: description
Dynamic: description-content-type
Dynamic: home-page
Dynamic: license
Dynamic: license-file
Dynamic: project-url
Dynamic: provides-extra
Dynamic: requires-dist
Dynamic: requires-python
Dynamic: summary
